Metadata-Version: 1.0
Name: WhooshAlchemy
Version: 0.1.4
Summary: Whoosh extension to SQLAlchemy
Home-page: https://github.com/sfermigier/WhooshAlchemy
Author: Stefane Fermigier
Author-email: sf@fermigier.com
License: BSD
Platform: any
Classifier: Intended Audience :: Developers
Classifier: License :: OSI Approved :: BSD License
Classifier: Operating System :: OS Independent
Classifier: Programming Language :: Python
Classifier: Topic :: Software Development :: Libraries :: Python Modules
